stix2gen/__init__.py
stix2gen/cli.py
stix2gen/ioc.py
stix2gen/version.py
stix2gen-1.0.dist-info/LICENSE
stix2gen-1.0.dist-info/METADATA
stix2gen-1.0.dist-info/WHEEL
stix2gen-1.0.dist-info/entry_points.txt
stix2gen-1.0.dist-info/top_level.txt
stix2gen-1.0.dist-info/RECORD
