Metadata-Version: 2.1
Name: stix2gen
Version: 1.0
Summary: stix2gen
Home-page: https://github.com/botherder/stix2gen
Author: Claudio Guarnieri
Author-email: nex@nex.sx
License: MIT
Keywords: security,forensics,malware
Platform: UNKNOWN
Classifier: Development Status :: 5 - Production/Stable
Classifier: Intended Audience :: Information Technology
Classifier: Operating System :: OS Independent
Classifier: Programming Language :: Python
License-File: LICENSE
Requires-Dist: click (>=8.1.3)
Requires-Dist: stix2 (>=3.0.1)
Requires-Dist: validators (>=0.20.0)
